{"accession":"BGC0002006","version":2,"changelog":{"releases":[{"version":"1","entries":[{"contributors":["AAAAAAAAAAAAAAAAAAAAAAAA"],"reviewers":["AAAAAAAAAAAAAAAAAAAAAAAA"],"date":"2019-10-16","comment":"Submitted"}],"date":"2019-10-16"}]},"quality":"questionable","status":"active","completeness":"unknown","loci":[{"accession":"NZ_CP033071.1","location":{"from":2833928,"to":2837273},"evidence":[]}],"biosynthesis":{"classes":[{"class":"ribosomal","subclass":"RiPP","precursors":[]}]},"compounds":[{"name":"albusnodin","evidence":[]}],"taxonomy":{"name":"Streptomyces albus","ncbiTaxId":1888},"legacy_references":["pubmed:29350227"]}