{"accession":"BGC0001586","version":3,"changelog":{"releases":[{"version":"1","entries":[{"contributors":["AAAAAAAAAAAAAAAAAAAAAAAA"],"reviewers":["AAAAAAAAAAAAAAAAAAAAAAAA"],"date":"2018-08-06","comment":"Submitted"}],"date":"2018-08-06"},{"version":"2","entries":[{"contributors":["AAAAAAAAAAAAAAAAAAAAAAAA"],"reviewers":["AAAAAAAAAAAAAAAAAAAAAAAA"],"date":"2019-10-16","comment":"Migrated from v1.4"}],"date":"2019-10-16"}]},"quality":"questionable","status":"active","completeness":"unknown","loci":[{"accession":"NZ_CP015641.1","location":{"from":3711099,"to":3730171},"evidence":[]}],"biosynthesis":{"classes":[{"class":"saccharide","glycosyltransferases":[]}]},"compounds":[{"name":"EPS273","evidence":[]}],"taxonomy":{"name":"Pseudomonas stutzeri","ncbiTaxId":316},"legacy_references":["pubmed:28698510"]}