{"accession":"BGC0001520","version":3,"changelog":{"releases":[{"version":"1","entries":[{"contributors":["AAAAAAAAAAAAAAAAAAAAAAAA"],"reviewers":["AAAAAAAAAAAAAAAAAAAAAAAA"],"date":"2018-08-06","comment":"Submitted"}],"date":"2018-08-06"},{"version":"2","entries":[{"contributors":["AAAAAAAAAAAAAAAAAAAAAAAA"],"reviewers":["AAAAAAAAAAAAAAAAAAAAAAAA"],"date":"2019-10-16","comment":"Migrated from v1.4"},{"contributors":["AAAAAAAAAAAAAAAAAAAAAAAA"],"reviewers":["AAAAAAAAAAAAAAAAAAAAAAAA"],"date":"2019-10-16","comment":"Updated compound(s) information (NPAtlas curation)"}],"date":"2019-10-16"},{"version":"3","entries":[{"contributors":["JR2IYHHUH7PHPG2DIF4WLYJO","4ZBJCWV5NZUBDJXCSIV4TKIA","4CEPXXFDQQ46VQJXBT4B4AUO"],"reviewers":["AAAAAAAAAAAAAAAAAAAAAAAA"],"date":"2024-07-26","comment":"MIBiG v4 annotathon"}],"date":"2024-11-15"}]},"quality":"questionable","status":"active","completeness":"unknown","loci":[{"accession":"LYMC01000002.1","location":{"from":865331,"to":945611},"evidence":[]}],"biosynthesis":{"classes":[{"class":"PKS","subclass":"Unknown","cyclases":[]}]},"compounds":[{"name":"aurantinin B","evidence":[{"method":"NMR","references":["doi:10.1021/jo00246a059"]}],"bioactivities":[{"name":"antibacterial","observed":true,"references":["doi:10.1021/acs.jafc.6b04455"],"assays":[{"concentration":"0.78 µg/mL","target":"antibacterial"}]}],"structure":"CC(CC(O)C(C)C(O)=O)C\\C(C)=C\\C=C\\C=C\\C1C(C)=CC2C(CCC(C)C2O[C@H]2O[C@@H](C)[C@H](O)C(=O)[C@@H]2O)C2\\C1=C1\\C(C)C(O)C\\C\\1=C(C)\\C(=O)OC2=O","databaseIds":["npatlas:NPA016670"],"mass":780.4084773599999,"formula":"C44H60O12"},{"name":"aurantinin C","evidence":[{"method":"NMR","references":["doi:10.1021/acs.jafc.6b04455"]}],"bioactivities":[{"name":"antibacterial","observed":true,"references":["doi:10.1021/acs.jafc.6b04455"],"assays":[{"concentration":"0.78 mg/mL","target":"antibacterial"}]}],"structure":"CC1=CC2C(CCC(C)C2O[C@H]2O[C@@H](C)[C@H](O)C(O)[C@@H]2O)C2C(=O)OC(=O)C(C)=C3CC(O)C(C)C3=C2C1/C=C/C=C/C=C(\\C)CC(C)CC(O)C(C)C(=O)O"},{"name":"aurantinin D","evidence":[{"method":"NMR","references":["doi:10.1021/acs.jafc.6b04455"]}],"bioactivities":[{"name":"antibacterial","observed":true,"references":["doi:10.1021/acs.jafc.6b04455"],"assays":[{"concentration":"0.78 µg/mL","target":"antibacterial"}]}]}],"taxonomy":{"name":"Bacillus subtilis","ncbiTaxId":1423},"legacy_references":["pubmed:27806569"]}