{"accession":"BGC0001661","version":5,"changelog":{"releases":[{"version":"1","entries":[{"contributors":["AAAAAAAAAAAAAAAAAAAAAAAA"],"reviewers":["AAAAAAAAAAAAAAAAAAAAAAAA"],"date":"2018-08-06","comment":"Submitted"}],"date":"2018-08-06"},{"version":"2","entries":[{"contributors":["AAAAAAAAAAAAAAAAAAAAAAAA"],"reviewers":["AAAAAAAAAAAAAAAAAAAAAAAA"],"date":"2019-10-16","comment":"Migrated from v1.4"},{"contributors":["AAAAAAAAAAAAAAAAAAAAAAAA"],"reviewers":["AAAAAAAAAAAAAAAAAAAAAAAA"],"date":"2019-10-16","comment":"Updated compound(s) information (NPAtlas curation)"}],"date":"2019-10-16"},{"version":"3","entries":[{"contributors":["AAAAAAAAAAAAAAAAAAAAAAAA"],"reviewers":["AAAAAAAAAAAAAAAAAAAAAAAA"],"date":"2022-09-15","comment":"Updated bioactivity data"}],"date":"2022-09-15"},{"version":"4","entries":[{"contributors":["AAAAAAAAAAAAAAAAAAAAAAAA"],"reviewers":["AAAAAAAAAAAAAAAAAAAAAAAA"],"date":"2022-10-07","comment":"Update chemical activity to schema version 2.11"}],"date":"2022-10-07"}]},"quality":"questionable","status":"active","completeness":"unknown","loci":[{"accession":"MG601230.1","location":{"from":0,"to":0},"evidence":[]}],"biosynthesis":{"classes":[{"class":"PKS","subclass":"Unknown","cyclases":[]}]},"compounds":[{"name":"mayamycin","evidence":[],"bioactivities":[{"name":{"activity":"antibacterial"},"observed":true,"references":[]}],"structure":"CN[C@@H]1C[C@@H](O[C@H](C)[C@H]1O)C1=C(O)C2=C(C(=O)C3=CC=CC(O)=C3C2=O)C2=C(O)C=C(C)C=C12","databaseIds":["npatlas:NPA01659"],"mass":463.1631021399999,"formula":"C26H25NO7"}],"taxonomy":{"name":"Streptomyces sp.","ncbiTaxId":1931},"legacy_references":["pubmed:29515228"]}