{"accession":"BGC0000502","version":5,"changelog":{"releases":[{"version":"1","entries":[{"contributors":["AAAAAAAAAAAAAAAAAAAAAAAA"],"reviewers":["AAAAAAAAAAAAAAAAAAAAAAAA"],"date":"2015-06-12","comment":"Submitted"}],"date":"2015-06-12"},{"version":"2","entries":[{"contributors":["AAAAAAAAAAAAAAAAAAAAAAAA"],"reviewers":["AAAAAAAAAAAAAAAAAAAAAAAA"],"date":"2019-10-16","comment":"Migrated from v1.4"}],"date":"2019-10-16"},{"version":"3","entries":[{"contributors":["AAAAAAAAAAAAAAAAAAAAAAAA"],"reviewers":["AAAAAAAAAAAAAAAAAAAAAAAA"],"date":"2022-09-15","comment":"Updated bioactivity data"}],"date":"2022-09-15"},{"version":"4","entries":[{"contributors":["AAAAAAAAAAAAAAAAAAAAAAAA"],"reviewers":["AAAAAAAAAAAAAAAAAAAAAAAA"],"date":"2022-10-07","comment":"Update chemical activity to schema version 2.11"}],"date":"2022-10-07"}]},"quality":"questionable","status":"active","completeness":"unknown","loci":[{"accession":"KJ000001.1","location":{"from":0,"to":0},"evidence":[]}],"biosynthesis":{"classes":[{"class":"ribosomal","subclass":"RiPP","precursors":[],"ripp_type":"Lanthipeptide"}]},"compounds":[{"name":"cerecidin","evidence":[],"bioactivities":[{"name":{"activity":"antibacterial"},"observed":true,"references":[]}]},{"name":"cerecidin A1","evidence":[]},{"name":"cerecidin A2","evidence":[]},{"name":"cerecidin A3","evidence":[]},{"name":"cerecidin A4","evidence":[]},{"name":"cerecidin A5","evidence":[]},{"name":"cerecidin A6","evidence":[]},{"name":"cerecidin A7","evidence":[]}],"taxonomy":{"name":"Bacillus cereus","ncbiTaxId":1396},"legacy_references":["pubmed:24532070"]}