{"accession":"BGC0001930","version":3,"changelog":{"releases":[{"version":"1","entries":[{"contributors":["AAAAAAAAAAAAAAAAAAAAAAAA"],"reviewers":["AAAAAAAAAAAAAAAAAAAAAAAA"],"date":"2019-10-16","comment":"Submitted"}],"date":"2019-10-16"},{"version":"2","entries":[{"contributors":["CUSGWVK3I4TVHJH7NHPFAP2L"],"reviewers":["AAAAAAAAAAAAAAAAAAAAAAAA"],"date":"2022-09-15","comment":"Fixed DOIs"},{"contributors":["SJG3CBEHSM6A3I74YXLH6GLA"],"reviewers":["AAAAAAAAAAAAAAAAAAAAAAAA"],"date":"2022-09-15","comment":"Retired as duplicate of BGC0001862"}],"date":"2022-09-15"}]},"quality":"questionable","status":"retired","completeness":"unknown","loci":[{"accession":"NZ_LVHY01000134.1","location":{"from":2400,"to":7600},"evidence":[]}],"biosynthesis":{"classes":[{"class":"ribosomal","subclass":"RiPP","precursors":[]}]},"compounds":[{"name":"pallidocin","evidence":[]}],"taxonomy":{"name":"Aeribacillus pallidus","ncbiTaxId":33936},"retirement_reasons":["Duplicate of BGC0001862"],"see_also":["BGC0001862"],"legacy_references":["doi:10.1038/s41467-019-09065-5"]}