{"accession":"BGC0001389","version":5,"changelog":{"releases":[{"version":"1","entries":[{"contributors":["AAAAAAAAAAAAAAAAAAAAAAAA"],"reviewers":["AAAAAAAAAAAAAAAAAAAAAAAA"],"date":"2016-09-03","comment":"Submitted"}],"date":"2016-09-03"},{"version":"2","entries":[{"contributors":["AAAAAAAAAAAAAAAAAAAAAAAA"],"reviewers":["AAAAAAAAAAAAAAAAAAAAAAAA"],"date":"2019-10-16","comment":"Migrated from v1.4"}],"date":"2019-10-16"},{"version":"3","entries":[{"contributors":["AAAAAAAAAAAAAAAAAAAAAAAA"],"reviewers":["AAAAAAAAAAAAAAAAAAAAAAAA"],"date":"2022-09-15","comment":"Updated bioactivity data"},{"contributors":["AAAAAAAAAAAAAAAAAAAAAAAA"],"reviewers":["AAAAAAAAAAAAAAAAAAAAAAAA"],"date":"2022-09-15","comment":"Added NRP substrate specificities"}],"date":"2022-09-15"},{"version":"4","entries":[{"contributors":["AAAAAAAAAAAAAAAAAAAAAAAA"],"reviewers":["AAAAAAAAAAAAAAAAAAAAAAAA"],"date":"2022-10-07","comment":"Update chemical activity to schema version 2.11"}],"date":"2022-10-07"},{"version":"5","entries":[{"contributors":["Z4WHVO6K4QR4NSPFS3BTTXEO"],"reviewers":["AAAAAAAAAAAAAAAAAAAAAAAA"],"date":"2024-04-23","comment":"MIBiG v4 annotathon"}],"date":"2024-11-15"}]},"quality":"questionable","status":"active","completeness":"unknown","loci":[{"accession":"KJ513094.1","location":{"from":0,"to":0},"evidence":[]}],"biosynthesis":{"classes":[{"class":"NRPS","subclass":"Type I"}],"modules":[{"type":"nrps-type1","name":"Unk01","genes":["AHZ34238.1"],"active":null,"carriers":[],"a_domain":{"type":"adenylation","gene":"AHZ34238.1","location":{"from":-1,"to":-1},"substrates":[{"name":"threonine","structure":"C[C@H]([C@@H](C(=O)O)N)O","proteinogenic":true}],"evidence":[{"method":"Structure-based inference"},{"method":"Sequence-based prediction"}]}},{"type":"nrps-type1","name":"Unk02","genes":["AHZ34238.1"],"active":null,"carriers":[],"a_domain":{"type":"adenylation","gene":"AHZ34238.1","location":{"from":-1,"to":-1},"substrates":[{"name":"proline","structure":"C1C[C@H](NC1)C(=O)O","proteinogenic":true}],"evidence":[{"method":"Structure-based inference"},{"method":"Sequence-based prediction"}]}},{"type":"nrps-type1","name":"Unk03","genes":["AHZ34238.1"],"active":null,"carriers":[],"a_domain":{"type":"adenylation","gene":"AHZ34238.1","location":{"from":-1,"to":-1},"substrates":[{"name":"alanine","structure":"C[C@@H](C(=O)O)N","proteinogenic":true}],"evidence":[{"method":"Structure-based inference"},{"method":"Sequence-based prediction"}]}},{"type":"nrps-type1","name":"Unk04","genes":["AHZ34238.1"],"active":null,"carriers":[],"a_domain":{"type":"adenylation","gene":"AHZ34238.1","location":{"from":-1,"to":-1},"substrates":[{"name":"alanine","structure":"C[C@@H](C(=O)O)N","proteinogenic":true}],"evidence":[{"method":"Structure-based inference"},{"method":"Sequence-based prediction"}]}},{"type":"nrps-type1","name":"Unk05","genes":["AHZ34239.1"],"active":null,"carriers":[],"a_domain":{"type":"adenylation","gene":"AHZ34239.1","location":{"from":-1,"to":-1},"substrates":[{"name":"alanine","structure":"C[C@@H](C(=O)O)N","proteinogenic":true}],"evidence":[{"method":"Structure-based inference"},{"method":"Sequence-based prediction"}]}},{"type":"nrps-type1","name":"Unk06","genes":["AHZ34239.1"],"active":null,"carriers":[],"a_domain":{"type":"adenylation","gene":"AHZ34239.1","location":{"from":-1,"to":-1},"substrates":[{"name":"alanine","structure":"C[C@@H](C(=O)O)N","proteinogenic":true}],"evidence":[{"method":"Structure-based inference"},{"method":"Sequence-based prediction"}]}},{"type":"nrps-type1","name":"Unk07","genes":["AHZ34239.1"],"active":null,"carriers":[],"a_domain":{"type":"adenylation","gene":"AHZ34239.1","location":{"from":-1,"to":-1},"substrates":[{"name":"valine","structure":"CC(C)[C@@H](C(=O)O)N","proteinogenic":true}],"evidence":[{"method":"Structure-based inference"},{"method":"Sequence-based prediction"}]}},{"type":"nrps-type1","name":"Unk08","genes":["AHZ34240.1"],"active":null,"carriers":[],"a_domain":{"type":"adenylation","gene":"AHZ34240.1","location":{"from":-1,"to":-1},"substrates":[{"name":"threonine","structure":"C[C@H]([C@@H](C(=O)O)N)O","proteinogenic":true}],"evidence":[{"method":"Structure-based inference"},{"method":"Sequence-based prediction"}]}},{"type":"nrps-type1","name":"Unk09","genes":["AHZ34240.1"],"active":null,"carriers":[],"a_domain":{"type":"adenylation","gene":"AHZ34240.1","location":{"from":-1,"to":-1},"substrates":[{"name":"glycine","structure":"NCC(=O)O","proteinogenic":true}],"evidence":[{"method":"Structure-based inference"},{"method":"Sequence-based prediction"}]}},{"type":"nrps-type1","name":"Unk10","genes":["AHZ34241.1"],"active":null,"carriers":[],"a_domain":{"type":"adenylation","gene":"AHZ34241.1","location":{"from":-1,"to":-1},"substrates":[{"name":"valine","structure":"CC(C)[C@@H](C(=O)O)N","proteinogenic":true}],"evidence":[{"method":"Structure-based inference"},{"method":"Sequence-based prediction"}]}},{"type":"nrps-type1","name":"Unk11","genes":["AHZ34241.1"],"active":null,"carriers":[],"a_domain":{"type":"adenylation","gene":"AHZ34241.1","location":{"from":-1,"to":-1},"substrates":[{"name":"isoleucine","structure":"CC[C@H](C)[C@@H](C(=O)O)N","proteinogenic":true}],"evidence":[{"method":"Structure-based inference"},{"method":"Sequence-based prediction"}]}},{"type":"nrps-type1","name":"Unk12","genes":["AHZ34241.1"],"active":null,"carriers":[],"a_domain":{"type":"adenylation","gene":"AHZ34241.1","location":{"from":-1,"to":-1},"substrates":[{"name":"glycine","structure":"NCC(=O)O","proteinogenic":true}],"evidence":[{"method":"Structure-based inference"},{"method":"Sequence-based prediction"}]}},{"type":"nrps-type1","name":"Unk13","genes":["AHZ34241.1"],"active":null,"carriers":[],"a_domain":{"type":"adenylation","gene":"AHZ34241.1","location":{"from":-1,"to":-1},"substrates":[{"name":"alanine","structure":"C[C@@H](C(=O)O)N","proteinogenic":true}],"evidence":[{"method":"Structure-based inference"},{"method":"Sequence-based prediction"}]}},{"type":"nrps-type1","name":"Unk14","genes":["AHZ34242.1"],"active":null,"carriers":[],"a_domain":{"type":"adenylation","gene":"AHZ34242.1","location":{"from":-1,"to":-1},"substrates":[{"name":"valine","structure":"CC(C)[C@@H](C(=O)O)N","proteinogenic":true}],"evidence":[{"method":"Structure-based inference"},{"method":"Sequence-based prediction"}]}},{"type":"nrps-type1","name":"Unk15","genes":["AHZ34242.1"],"active":null,"carriers":[],"a_domain":{"type":"adenylation","gene":"AHZ34242.1","location":{"from":-1,"to":-1},"substrates":[{"name":"alanine","structure":"C[C@@H](C(=O)O)N","proteinogenic":true}],"evidence":[{"method":"Structure-based inference"},{"method":"Sequence-based prediction"}]}},{"type":"nrps-type1","name":"Unk16","genes":["AHZ34242.1"],"active":null,"carriers":[],"a_domain":{"type":"adenylation","gene":"AHZ34242.1","location":{"from":-1,"to":-1},"substrates":[{"name":"valine","structure":"CC(C)[C@@H](C(=O)O)N","proteinogenic":true}],"evidence":[{"method":"Structure-based inference"},{"method":"Sequence-based prediction"}]}},{"type":"nrps-type1","name":"Unk17","genes":["AHZ34243.1"],"active":null,"carriers":[],"a_domain":{"type":"adenylation","gene":"AHZ34243.1","location":{"from":-1,"to":-1},"substrates":[{"name":"threonine","structure":"C[C@H]([C@@H](C(=O)O)N)O","proteinogenic":true}],"evidence":[{"method":"Structure-based inference"},{"method":"Sequence-based prediction"}]}},{"type":"nrps-type1","name":"Unk18","genes":["AHZ34243.1"],"active":null,"carriers":[],"a_domain":{"type":"adenylation","gene":"AHZ34243.1","location":{"from":-1,"to":-1},"substrates":[{"name":"threonine","structure":"C[C@H]([C@@H](C(=O)O)N)O","proteinogenic":true}],"evidence":[{"method":"Structure-based inference"},{"method":"Sequence-based prediction"}]}},{"type":"nrps-type1","name":"Unk19","genes":["AHZ34243.1"],"active":null,"carriers":[],"a_domain":{"type":"adenylation","gene":"AHZ34243.1","location":{"from":-1,"to":-1},"substrates":[{"name":"alanine","structure":"C[C@@H](C(=O)O)N","proteinogenic":true}],"evidence":[{"method":"Structure-based inference"},{"method":"Sequence-based prediction"}]}},{"type":"nrps-type1","name":"Unk20","genes":["AHZ34243.1"],"active":null,"carriers":[],"a_domain":{"type":"adenylation","gene":"AHZ34243.1","location":{"from":-1,"to":-1},"substrates":[{"name":"2,4-diaminobutyric acid","structure":"C(CN)[C@@H](C(=O)O)N","proteinogenic":false}],"evidence":[{"method":"Structure-based inference"},{"method":"Sequence-based prediction"}]}},{"type":"nrps-type1","name":"Unk21","genes":["AHZ34243.1"],"active":null,"carriers":[],"a_domain":{"type":"adenylation","gene":"AHZ34243.1","location":{"from":-1,"to":-1},"substrates":[{"name":"serine","structure":"C([C@@H](C(=O)O)N)O","proteinogenic":true}],"evidence":[{"method":"Structure-based inference"},{"method":"Sequence-based prediction"}]}},{"type":"nrps-type1","name":"Unk22","genes":["AHZ34243.1"],"active":null,"carriers":[],"a_domain":{"type":"adenylation","gene":"AHZ34243.1","location":{"from":-1,"to":-1},"substrates":[{"name":"isoleucine","structure":"CC[C@H](C)[C@@H](C(=O)O)N","proteinogenic":true},{"name":"valine","structure":"CC(C)[C@@H](C(=O)O)N","proteinogenic":true},{"name":"leucine","structure":"CC(C)C[C@@H](C(=O)O)N","proteinogenic":true}],"evidence":[{"method":"Structure-based inference"},{"method":"Sequence-based prediction"}]}}]},"compounds":[{"name":"cichopeptin A","evidence":[{"method":"MS/MS","references":["doi:10.1094/mpmi-03-15-0061-r"]}],"classes":["Depsipeptide","Lipopeptide"],"cyclic":true,"mass":2066.2,"formula":"C97H161N23O26"},{"name":"cichopeptin B","evidence":[{"method":"MS/MS","references":["doi:10.1094/mpmi-03-15-0061-r"]}],"classes":["Depsipeptide","Lipopeptide"],"cyclic":true,"mass":2052.4,"formula":"C96H159N23O26"}],"taxonomy":{"name":"Pseudomonas cichorii","ncbiTaxId":36746},"legacy_references":["pubmed:25961750"]}