{"accession":"BGC0001652","version":5,"changelog":{"releases":[{"version":"1","entries":[{"contributors":["AAAAAAAAAAAAAAAAAAAAAAAA"],"reviewers":["AAAAAAAAAAAAAAAAAAAAAAAA"],"date":"2018-08-06","comment":"Submitted"}],"date":"2018-08-06"},{"version":"2","entries":[{"contributors":["AAAAAAAAAAAAAAAAAAAAAAAA"],"reviewers":["AAAAAAAAAAAAAAAAAAAAAAAA"],"date":"2019-10-16","comment":"Migrated from v1.4"},{"contributors":["AAAAAAAAAAAAAAAAAAAAAAAA"],"reviewers":["AAAAAAAAAAAAAAAAAAAAAAAA"],"date":"2019-10-16","comment":"Updated compound(s) information (NPAtlas curation)"}],"date":"2019-10-16"},{"version":"3","entries":[{"contributors":["AAAAAAAAAAAAAAAAAAAAAAAA"],"reviewers":["AAAAAAAAAAAAAAAAAAAAAAAA"],"date":"2022-09-15","comment":"Updated bioactivity data"}],"date":"2022-09-15"},{"version":"4","entries":[{"contributors":["AAAAAAAAAAAAAAAAAAAAAAAA"],"reviewers":["AAAAAAAAAAAAAAAAAAAAAAAA"],"date":"2022-10-07","comment":"Update chemical activity to schema version 2.11"}],"date":"2022-10-07"}]},"quality":"questionable","status":"active","completeness":"unknown","loci":[{"accession":"KT381463.1","location":{"from":0,"to":0},"evidence":[]}],"biosynthesis":{"classes":[{"class":"NRPS","subclass":"Type I"}]},"compounds":[{"name":"limazepine C","evidence":[],"bioactivities":[{"name":{"activity":"antibacterial"},"observed":true,"references":[]},{"name":{"activity":"cytotoxic"},"observed":true,"references":[]}],"structure":"[H][C@@]12CC(CC)=CN1C(=O)C1=CC=C(OC)C(O)=C1N=C2","databaseIds":["npatlas:NPA016210"],"mass":272.116092372,"formula":"C15H16N2O3"},{"name":"limazepine D","evidence":[],"bioactivities":[{"name":{"activity":"antibacterial"},"observed":true,"references":[]},{"name":{"activity":"cytotoxic"},"observed":true,"references":[]}],"structure":"CCC1=CN2C(=C1)C=NC1=C(O)C(OC)=CC=C1C2=O","databaseIds":["npatlas:NPA012119"],"mass":270.100442308,"formula":"C15H14N2O3"},{"name":"limazepine E","evidence":[],"bioactivities":[{"name":{"activity":"antibacterial"},"observed":true,"references":[]},{"name":{"activity":"cytotoxic"},"observed":true,"references":[]}],"structure":"[H][C@@]12C\\C(CN1C(=O)C1=CC=C(OC)C(O)=C1N=C2)=C/C","databaseIds":["npatlas:NPA019802"],"mass":272.116092372,"formula":"C15H16N2O3"},{"name":"limazepine F","evidence":[],"bioactivities":[{"name":{"activity":"antibacterial"},"observed":true,"references":[]},{"name":{"activity":"cytotoxic"},"observed":true,"references":[]}],"structure":"[H][C@@]12C\\C(CN1C(=O)C1=CC=CC=C1N[C@@H]2O)=C/C","databaseIds":["npatlas:NPA01599"],"mass":244.121177752,"formula":"C14H16N2O2"},{"name":"limazepine A","evidence":[],"bioactivities":[{"name":{"activity":"antibacterial"},"observed":true,"references":[]},{"name":{"activity":"cytotoxic"},"observed":true,"references":[]}],"structure":"[H][C@@]12CC(CC)=CN1C(=O)C1=CC=C(OC)C(O)=C1NC2=O","databaseIds":["npatlas:NPA07410"],"mass":288.111006992,"formula":"C15H16N2O4"}],"taxonomy":{"name":"Streptomyces sp. ICBB 8177","ncbiTaxId":563922},"legacy_references":["pubmed:29517100"]}