{"accession":"BGC0002415","version":2,"changelog":{"releases":[{"version":"1","entries":[{"contributors":["AAAAAAAAAAAAAAAAAAAAAAAA"],"reviewers":["AAAAAAAAAAAAAAAAAAAAAAAA"],"date":"2022-09-15","comment":"Entry added"}],"date":"2022-09-15"}]},"quality":"questionable","status":"active","completeness":"unknown","loci":[{"accession":"CP030789.1","location":{"from":1592806,"to":1607403},"evidence":[]}],"biosynthesis":{"classes":[{"class":"NRPS","subclass":"Type I"}]},"compounds":[{"name":"vanchrobactin","evidence":[],"structure":"C1=CC(=C(C(=C1)O)O)C(=O)N[C@H](CCCN=C(N)N)C(=O)N[C@@H](CO)C(=O)O","databaseIds":["npatlas:NPA016075"]},{"name":"trivanchrobactin","evidence":[],"structure":"C1=CC(=C(C(=C1)O)O)C(=O)N[C@H](CCCN=C(N)N)C(=O)N[C@@H](CO)C(=O)OC[C@@H](C(=O)OC[C@@H](C(=O)O)NC(=O)[C@@H](CCCN=C(N)N)NC(=O)C2=C(C(=CC=C2)O)O)NC(=O)[C@@H](CCCN=C(N)N)NC(=O)C3=C(C(=CC=C3)O)O","databaseIds":["npatlas:NPA018703"]},{"name":"divanchrobactin","evidence":[],"structure":"C1=CC(=C(C(=C1)O)O)C(=O)N[C@H](CCCN=C(N)N)C(=O)N[C@@H](CO)C(=O)OC[C@@H](C(=O)O)NC(=O)[C@@H](CCCN=C(N)N)NC(=O)C2=C(C(=CC=C2)O)O","databaseIds":["npatlas:NPA019471"]}],"taxonomy":{"name":"Vibrio campbellii","ncbiTaxId":680},"legacy_references":["pubmed:22275102","doi:10.1128/JB.06583-11"]}