{"accession":"BGC0003079","version":1,"changelog":{"releases":[{"version":"1","entries":[{"contributors":["PBAWZHQJVWWPNLTYHKMZXYFE","GOLYTYSBLVQXLD5R6Y4RMO7M"],"reviewers":["AAAAAAAAAAAAAAAAAAAAAAAA"],"date":"2024-05-14","comment":"MIBiG v4 annotathon"}],"date":"2024-11-15"}]},"quality":"high","status":"pending","completeness":"complete","loci":[{"accession":"NZ_AUBE01000003.1","location":{"from":139439,"to":141323},"evidence":[{"method":"Heterologous expression","references":["doi:10.1002/anie.202200377"]}]}],"biosynthesis":{"classes":[{"class":"NRPS","subclass":"Type V"}]},"compounds":[{"name":"mycocyclosin","evidence":[{"method":"NMR","references":["doi:10.1002/anie.202200377"]},{"method":"Mass spectrometry","references":["doi:10.1002/anie.202200377"]}],"classes":["Tyrosine-derived","Diketopiperazine"],"structure":"C1[C@H]2C(=O)N[C@@H](CC3=CC(=C(C=C3)O)C4=C(C=CC1=C4)O)C(=O)N2","cyclic":true,"mass":324.111,"formula":"C18H16N2O4"},{"name":"guatyromycine A","evidence":[{"method":"NMR","references":["doi:10.1002/anie.202200377"]},{"method":"Mass spectrometry","references":["doi:10.1002/anie.202200377"]}],"classes":["Tyrosine-derived","Diketopiperazine"],"structure":"O=C([C@H](CC1=CC=C(OC2=NC(C(NC(N)=N3)=O)=C3N2)C=C1)N4)N[C@@H](CC5=CC=C(O)C=C5)C4=O","cyclic":true,"mass":475.1604,"formula":"C23H21N7O5"},{"name":"guatyromycine B","evidence":[{"method":"NMR","references":["doi:10.1002/anie.202200377"]},{"method":"NMR","references":["doi:10.1002/anie.202200377"]}],"classes":["Tyrosine-derived","Diketopiperazine"],"structure":"O=C([C@H](CC1=CC=C(OC2=NC(NC=N3)=C3C(N2)=O)C=C1)N4)N[C@@H](CC5=CC=C(O)C=C5)C4=O","cyclic":true,"mass":460.1495,"formula":"C23H20N6O5"}],"taxonomy":{"name":"Streptomyces flavidovirens DSM 40150","ncbiTaxId":1123320}}