{"accession":"BGC0001500","version":3,"changelog":{"releases":[{"version":"1","entries":[{"contributors":["AAAAAAAAAAAAAAAAAAAAAAAA"],"reviewers":["AAAAAAAAAAAAAAAAAAAAAAAA"],"date":"2018-08-06","comment":"Submitted"}],"date":"2018-08-06"},{"version":"2","entries":[{"contributors":["AAAAAAAAAAAAAAAAAAAAAAAA"],"reviewers":["AAAAAAAAAAAAAAAAAAAAAAAA"],"date":"2019-10-16","comment":"Migrated from v1.4"},{"contributors":["AAAAAAAAAAAAAAAAAAAAAAAA"],"reviewers":["AAAAAAAAAAAAAAAAAAAAAAAA"],"date":"2019-10-16","comment":"Updated reference publication(s) (MIBiG Annotathon)"}],"date":"2019-10-16"},{"version":"3","entries":[{"contributors":["WO7I2Z66IEAZGQEL4YNOH36C","4CEPXXFDQQ46VQJXBT4B4AUO"],"reviewers":["AAAAAAAAAAAAAAAAAAAAAAAA"],"date":"2024-05-13","comment":"MIBiG v4 annotathon"}],"date":"2024-11-15"}]},"quality":"questionable","status":"active","completeness":"unknown","loci":[{"accession":"KT996129.1","location":{"from":0,"to":0},"evidence":[]}],"biosynthesis":{"classes":[{"class":"PKS","subclass":"Unknown","cyclases":[]}]},"compounds":[{"name":"allocyclinone A","evidence":[{"method":"NMR","references":["doi:10.1038/ja.2016.62"]}],"classes":["Aromatic polyketide"],"bioactivities":[{"name":"antibacterial","observed":true,"references":["doi:10.1038/ja.2016.62"]},{"name":"antibacterial","observed":true,"references":["doi:10.1038/ja.2016.62"]}],"structure":"O=C(C(C=CC1=C2C(OC)=C(Cl)C(C(Cl)(Cl)Cl)=C1)=C2C3=O)C4=C3C(O)=C(C(OC5(OC)C)=O)C5=C4O","databaseIds":["npatlas:NPA021547"],"mass":571.94,"formula":" C24H14Cl4O8"},{"name":"allocyclinone B","evidence":[{"method":"NMR","references":["doi:10.1038/ja.2016.62"]}],"classes":["Aromatic polyketide"],"structure":"O=C(C(C=CC1=C2C(OC)=C(Cl)C(C)=C1)=C2C3=O)C4=C3C(O)=C(C(OC5(OC)C)=O)C5=C4O","databaseIds":["npatlas:NPA021548"],"mass":468.06,"formula":" C24H17ClO8"},{"name":"allocyclinone C","evidence":[{"method":"NMR","references":["doi:10.1038/ja.2016.62"]}],"classes":["Aromatic polyketide"],"bioactivities":[{"name":"antibacterial","observed":true,"references":["doi:10.1038/ja.2016.62"]}],"structure":"O=C(C(C=CC1=C2C(OC)=C(Cl)C(CCl)=C1)=C2C3=O)C4=C3C(O)=C(C(OC5(OC)C)=O)C5=C4O","databaseIds":["npatlas:NPA021549"],"mass":502.02,"formula":" C24H16Cl2O8"},{"name":"allocyclinone D","evidence":[{"method":"NMR","references":["doi:10.1038/ja.2016.62"]}],"classes":["Aromatic polyketide"],"bioactivities":[{"name":"antibacterial","observed":true,"references":["doi:10.1038/ja.2016.62"]}],"structure":"O=C(C(C=CC1=C2C(OC)=C(Cl)C(C(Cl)Cl)=C1)=C2C3=O)C4=C3C(O)=C(C(OC5(OC)C)=O)C5=C4O","databaseIds":["npatlas:NPA021550"],"mass":535.98,"formula":" C24H15Cl3O8"}],"taxonomy":{"name":"Actinoallomurus sp. ID145698","ncbiTaxId":1820605},"legacy_references":["doi:10.26434/chemrxiv.5346739.v1"]}